lanthanum
